{
  "openapi": "3.0.2",
  "info": {
    "title": "cirrus API",
    "version": "1.0"
  },
  "tags": [
    {
      "name": "users",
      "description": "User management"
    }
  ],
  "components": {
    "securitySchemes": {
      "BearerAuth": {
        "type": "http",
        "scheme": "bearer"
      }
    },
    "schemas": {
      "Error": {
        "type": "object",
        "properties": {
          "message": {
            "type": "string"
          }
        }
      },
      "CreateUserRequest": {
        "type": "object",
        "required": [
          "email",
          "password"
        ],
        "properties": {
          "email": {
            "type": "string"
          },
          "password": {
            "type": "string"
          }
        }
      },
      "User": {
        "type": "object",
        "properties": {
          "email": {
            "type": "string"
          }
        }
      }
    }
  },
  "security": [
    {
      "BearerAuth": []
    }
  ],
  "paths": {
    "/users": {
      "get": {
        "description": "Get own user info",
        "tags": [
          "users"
        ],
        "responses": {
          "200": {
            "description": "Successfully retrieve the user own information",
            "content": {
              "application/json": {
                "schema": {
                  "$ref": "#/components/schemas/User"
                }
              }
            }
          },
          "default": {
            "description": "Error",
            "content": {
              "application/json": {
                "schema": {
                  "$ref": "#/components/schemas/Error"
                }
              }
            }
          }
        }
      },
      "post": {
        "description": "Create a new user",
        "tags": [
          "users"
        ],
        "security": [],
        "requestBody": {
          "required": true,
          "content": {
            "application/json": {
              "schema": {
                "$ref": "#/components/schemas/CreateUserRequest"
              }
            }
          }
        },
        "responses": {
          "200": {
            "description": "User successfully created"
          },
          "default": {
            "$ref": "#/paths/~1users/get/responses/default"
          }
        }
      }
    }
  }
}
